pydocxtpl/__init__.py
pydocxtpl/ext.py
pydocxtpl/node.py
pydocxtpl/table.py
pydocxtpl/text.py
pydocxtpl/utils.py
pydocxtpl/writer.py
pydocxtpl-0.2.1.dist-info/LICENSE
pydocxtpl-0.2.1.dist-info/METADATA
pydocxtpl-0.2.1.dist-info/WHEEL
pydocxtpl-0.2.1.dist-info/top_level.txt
pydocxtpl-0.2.1.dist-info/RECORD
