Metadata-Version: 2.1
Name: pydocxtpl
Version: 0.2.1
Summary: A python module to generate docx files from a docx template
Home-page: https://github.com/zhangyu836/python-docx-templater
Author: Zhang Yu
Author-email: zhangyu836@gmail.com
License: MIT
Keywords: Word,docx,template
Platform: Any platform 
Requires-Dist: python-docx (>=0.8.10)
Requires-Dist: jinja2
Requires-Dist: six
